PythonZyjTools/__init__.py
PythonZyjTools/Base/__init__.py
PythonZyjTools/Base/getconfig.py
PythonZyjTools/Base/tools.py
PythonZyjTools/DbConnect/__init__.py
PythonZyjTools/DbConnect/db_config.py
PythonZyjTools/DbConnect/mysql_date_mode.py
PythonZyjTools/DbConnect/mysql_drivers.py
PythonZyjTools/DbConnect/mysql_sql_tools.py
PythonZyjTools/DbConnect/sqlalchemy_drivers.py
PythonZyjTools/DbConnect/sqltools.py
PythonZyjTools/Email/__init__.py
PythonZyjTools/Email/config.py
PythonZyjTools/Email/respond.py
PythonZyjTools/Email/send.py
PythonZyjTools/LinuxConnect/__init__.py
PythonZyjTools/LinuxConnect/dowload.py
PythonZyjTools/LinuxConnect/drivers.py
PythonZyjTools/LinuxConnect/exec_cmd.py
PythonZyjTools/LinuxConnect/get_info.py
PythonZyjTools/LinuxConnect/security.py
PythonZyjTools/LinuxConnect/upload.py
PythonZyjTools/Office/__init__.py
PythonZyjTools/Office/execl_read.py
PythonZyjTools/Office/execl_write.py
PythonZyjTools/get_ip_info/__init__.py
PythonZyjTools/get_ip_info/chuli_data.py
PythonZyjTools/get_ip_info/get_info.py
PythonZyjTools/get_ip_info/get_ip_data_mode.py
PythonZyjTools/get_ip_info/main.py
PythonZyjTools/get_ip_info/message_send.py
PythonZyjTools-1.0.0.dist-info/LICENSE
PythonZyjTools-1.0.0.dist-info/METADATA
PythonZyjTools-1.0.0.dist-info/WHEEL
PythonZyjTools-1.0.0.dist-info/top_level.txt
PythonZyjTools-1.0.0.dist-info/RECORD
